nya/__init__.py
nya/_version.py
nya/config.yaml
nya/schema.json
nya/common/__init__.py
nya/common/constants.py
nya/common/exceptions.py
nya/common/models.py
nya/config/__init__.py
nya/config/manager.py
nya/core/__init__.py
nya/core/control.py
nya/core/handler.py
nya/core/proxy.py
nya/core/queue.py
nya/core/request.py
nya/core/streaming.py
nya/dashboard/__init__.py
nya/dashboard/api.py
nya/html/favicon.ico
nya/html/index.html
nya/html/login.html
nya/html/static/logo.svg
nya/html/static/css/styles.css
nya/html/static/js/dashboard.js
nya/server/__init__.py
nya/server/app.py
nya/server/auth.py
nya/services/__init__.py
nya/services/lb.py
nya/services/limit.py
nya/services/metrics.py
nya/utils/__init__.py
nya/utils/header.py
nya/utils/helper.py
nya_proxy-0.4.6.dist-info/licenses/LICENSE
nya_proxy-0.4.6.dist-info/METADATA
nya_proxy-0.4.6.dist-info/WHEEL
nya_proxy-0.4.6.dist-info/entry_points.txt
nya_proxy-0.4.6.dist-info/top_level.txt
nya_proxy-0.4.6.dist-info/RECORD
