Metadata-Version: 2.4
Name: nya-proxy
Version: 0.4.6
Summary: A lightweight, flexible API proxy with dynamic token rotation, load balancing, and rate limiting capabilities.
Author-email: "Nya Foundation Team (k3scat)" <k3scat@gmail.com>
License-Expression: MIT
Project-URL: Homepage, https://github.com/Nya-Foundation/nyaproxy
Project-URL: Bug Tracker, https://github.com/Nya-Foundation/nyaproxy/issues
Classifier: Development Status :: 4 - Beta
Classifier: Intended Audience :: Developers
Classifier: Programming Language :: Python :: 3
Classifier: Programming Language :: Python :: 3.10
Classifier: Programming Language :: Python :: 3.11
Classifier: Programming Language :: Python :: 3.12
Classifier: Programming Language :: Python :: 3.13
Requires-Python: >=3.10
License-File: LICENSE
Requires-Dist: fastapi>=0.100.0
Requires-Dist: uvicorn>=0.22.0
Requires-Dist: httpx[socks]>=0.24.0
Requires-Dist: setuptools>=42.0.0
Requires-Dist: watchfiles>=0.18.0
Requires-Dist: jmespath>=1.0.1
Requires-Dist: orjson<4,>=3.10
Requires-Dist: loguru>=0.7.0
Requires-Dist: nekoconf[remote,schema,server]==1.2.1
Provides-Extra: dev
Requires-Dist: pytest>=7.0.0; extra == "dev"
Requires-Dist: pytest-asyncio>=0.21.0; extra == "dev"
Requires-Dist: pytest-cov>=4.0.0; extra == "dev"
Requires-Dist: pytest-mock>=3.10.0; extra == "dev"
Requires-Dist: aioresponses>=0.7.4; extra == "dev"
Provides-Extra: lint
Requires-Dist: flake8>=6.0.0; extra == "lint"
Requires-Dist: black>=23.0.0; extra == "lint"
Requires-Dist: isort>=5.0.0; extra == "lint"
Dynamic: license-file
